pioneer/das/api/__init__.py
pioneer/das/api/categories.py
pioneer/das/api/dataset_format_converter.py
pioneer/das/api/datatypes.py
pioneer/das/api/interpolators.py
pioneer/das/api/lane_types.py
pioneer/das/api/loaders.py
pioneer/das/api/platform.py
pioneer/das/api/datasources/__init__.py
pioneer/das/api/datasources/abstract_datasource.py
pioneer/das/api/datasources/datasource.py
pioneer/das/api/datasources/datasource_wrapper.py
pioneer/das/api/datasources/virtual_datasources/__init__.py
pioneer/das/api/datasources/virtual_datasources/bounding_box_metadata.py
pioneer/das/api/datasources/virtual_datasources/cylindrical_projection.py
pioneer/das/api/datasources/virtual_datasources/echoes_from_traces.py
pioneer/das/api/datasources/virtual_datasources/echoes_with_pulses.py
pioneer/das/api/datasources/virtual_datasources/hdr_waveform.py
pioneer/das/api/datasources/virtual_datasources/point_cloud_fusion.py
pioneer/das/api/datasources/virtual_datasources/rgb_cloud.py
pioneer/das/api/datasources/virtual_datasources/virtual_datasource.py
pioneer/das/api/datasources/virtual_datasources/voxel_map.py
pioneer/das/api/datasources/virtual_datasources/waveform_cloud.py
pioneer/das/api/egomotion/__init__.py
pioneer/das/api/egomotion/carla_egomotion_provider.py
pioneer/das/api/egomotion/egomotion_provider.py
pioneer/das/api/egomotion/imu_egomotion_provider.py
pioneer/das/api/egomotion/vaya_egomotion_provider.py
pioneer/das/api/samples/__init__.py
pioneer/das/api/samples/echo.py
pioneer/das/api/samples/fast_trace.py
pioneer/das/api/samples/image.py
pioneer/das/api/samples/image_cylinder.py
pioneer/das/api/samples/image_fisheye.py
pioneer/das/api/samples/point_cloud.py
pioneer/das/api/samples/sample.py
pioneer/das/api/samples/trace.py
pioneer/das/api/samples/xyzit.py
pioneer/das/api/samples/xyzv.py
pioneer/das/api/samples/annotations/__init__.py
pioneer/das/api/samples/annotations/box_2d.py
pioneer/das/api/samples/annotations/box_3d.py
pioneer_das_api-1.4.4.dist-info/DESCRIPTION.rst
pioneer_das_api-1.4.4.dist-info/METADATA
pioneer_das_api-1.4.4.dist-info/RECORD
pioneer_das_api-1.4.4.dist-info/WHEEL
pioneer_das_api-1.4.4.dist-info/dependency_links.txt
pioneer_das_api-1.4.4.dist-info/metadata.json
pioneer_das_api-1.4.4.dist-info/top_level.txt
