Metadata-Version: 2.0
Name: pioneer-das-api
Version: 1.4.4
Summary: Pioneer's das api
Home-page: UNKNOWN
Author: Leddartech
License: UNKNOWN
Platform: UNKNOWN
Classifier: Programming Language :: Python :: 3
Classifier: License :: OSI Approved :: MIT License
Classifier: Operating System :: OS Independent
Requires-Python: >=3.6
Requires-Dist: Cython
Requires-Dist: numpy
Requires-Dist: open3d
Requires-Dist: opencv-python
Requires-Dist: pandas
Requires-Dist: pioneer-common (>=1.0)
Requires-Dist: pyyaml
Requires-Dist: ruamel.std.zipfile
Requires-Dist: scipy
Requires-Dist: six
Requires-Dist: sklearn
Requires-Dist: tqdm
Requires-Dist: transforms3d
Requires-Dist: utm
